protorpc/__init__.py
protorpc/definition.py
protorpc/definition_test.py
protorpc/descriptor.py
protorpc/descriptor_test.py
protorpc/end2end_test.py
protorpc/generate.py
protorpc/generate_proto.py
protorpc/generate_proto_test.py
protorpc/generate_python.py
protorpc/generate_python_test.py
protorpc/generate_test.py
protorpc/google_imports.py
protorpc/message_types.py
protorpc/message_types_test.py
protorpc/messages.py
protorpc/messages_test.py
protorpc/non_sdk_imports.py
protorpc/protobuf.py
protorpc/protobuf_test.py
protorpc/protojson.py
protorpc/protojson_test.py
protorpc/protorpc_test_pb2.py
protorpc/protourlencode.py
protorpc/protourlencode_test.py
protorpc/registry.py
protorpc/registry_test.py
protorpc/remote.py
protorpc/remote_test.py
protorpc/test_util.py
protorpc/transport.py
protorpc/transport_test.py
protorpc/util.py
protorpc/util_test.py
protorpc/webapp_test_util.py
protorpc/_google/__init__.py
protorpc/_google/net/__init__.py
protorpc/_google/net/proto/ProtocolBuffer.py
protorpc/_google/net/proto/RawMessage.py
protorpc/_google/net/proto/__init__.py
protorpc/_google/net/proto/message_set.py
protorpc/experimental/__init__.py
protorpc/webapp/__init__.py
protorpc/webapp/forms.py
protorpc/webapp/forms_test.py
protorpc/webapp/google_imports.py
protorpc/webapp/service_handlers.py
protorpc/webapp/service_handlers_test.py
protorpc/wsgi/__init__.py
protorpc/wsgi/service.py
protorpc/wsgi/service_test.py
protorpc/wsgi/util.py
protorpc/wsgi/util_test.py
protorpc_standalone-0.12.0a2.dist-info/LICENSE
protorpc_standalone-0.12.0a2.dist-info/METADATA
protorpc_standalone-0.12.0a2.dist-info/WHEEL
protorpc_standalone-0.12.0a2.dist-info/entry_points.txt
protorpc_standalone-0.12.0a2.dist-info/top_level.txt
protorpc_standalone-0.12.0a2.dist-info/RECORD
