Metadata-Version: 2.1
Name: protorpc-standalone
Version: 0.12.0a2
Summary: Google Protocol RPC
Home-page: http://code.google.com/p/google-protorpc/
Author: Google Inc.
Author-email: rafek@google.com
License: Apache 2.0
Keywords: google protocol rpc
Platform: UNKNOWN
Classifier: Intended Audience :: Developers
Classifier: License :: OSI Approved :: Apache Software License
Classifier: Operating System :: MacOS :: MacOS X
Classifier: Operating System :: Microsoft :: Windows
Classifier: Operating System :: POSIX :: Linux
Classifier: Programming Language :: Python :: 3
Classifier: Programming Language :: Python :: 3.7
Classifier: Topic :: Software Development :: Libraries
Classifier: Topic :: Software Development :: Libraries :: Python Modules
Requires-Dist: six (>=1.7.0)
